pet/__init__.py
pet/analysis.py
pet/data_preparation.py
pet/estimate_error.py
pet/estimate_error_sp.py
pet/hypers.py
pet/long_range.py
pet/molecule.py
pet/neighbors_convert.cpp
pet/neighbors_convert.so
pet/pet.py
pet/pet_sp.py
pet/single_struct_calculator.py
pet/sp_frames_calculator.py
pet/train_model.py
pet/train_model_general_target.py
pet/transformer.py
pet/utilities.py
pet/zbl.py
pet_torch-0.0.0.dist-info/LICENSE.md
pet_torch-0.0.0.dist-info/METADATA
pet_torch-0.0.0.dist-info/WHEEL
pet_torch-0.0.0.dist-info/entry_points.txt
pet_torch-0.0.0.dist-info/top_level.txt
pet_torch-0.0.0.dist-info/RECORD
